DjangoModelTracker-1.2.0.dist-info/DESCRIPTION.rst
DjangoModelTracker-1.2.0.dist-info/METADATA
DjangoModelTracker-1.2.0.dist-info/RECORD
DjangoModelTracker-1.2.0.dist-info/WHEEL
DjangoModelTracker-1.2.0.dist-info/metadata.json
DjangoModelTracker-1.2.0.dist-info/top_level.txt
ModelTracker/Tracker.py
ModelTracker/__init__.py
ModelTracker/middleware.py
ModelTracker/models.py
ModelTracker/urls.py
ModelTracker/views.py
ModelTracker/migrations/0001_initial.py
ModelTracker/migrations/0002_auto_20160929_0517.py
ModelTracker/migrations/0003_history_related_objects.py
ModelTracker/migrations/__init__.py
ModelTracker/templates/main.html
