Metadata-Version: 2.0
Name: DjangoModelTracker
Version: 1.2.0
Summary: Track Django Model Objects over time
Home-page: https://github.com/mkalioby/ModelTracker/
Author: Mohamed El-Kalioby
Author-email: mkalioby@mkalioby.com
License: MIT
Download-URL: https://github.com/mkalioby/ModelTracker/
Platform: UNKNOWN
Requires-Dist: Django (>=1.7)
Requires-Dist: jsonfield
Requires-Dist: simplejson
